<?xml version="1.0" encoding="utf-8"?>
<IncrementalBankBuild Version="6" Flags="601859981">
	<Platform GUID="{219BD3F6-D1CA-47FA-A62C-2B3B0EC42804}">
		<Banks>
			<Language ID="393239870">
				<File Name="Blorg" Hash="1499106286" Timestamp="1599315367"/>
				<File Name="Init" Hash="3121226777" Timestamp="1599315367"/>
			</Language>
		</Banks>
		<XMLInfo>
			<Language ID="-1">
				<File Name="" Hash="1300315220" Timestamp="1599315367"/>
			</Language>
		</XMLInfo>
	</Platform>
</IncrementalBankBuild>
